simple_asr/__init__.py
simple_asr/blank.py
simple_asr-0.0.1.dist-info/LICENSE
simple_asr-0.0.1.dist-info/METADATA
simple_asr-0.0.1.dist-info/WHEEL
simple_asr-0.0.1.dist-info/entry_points.txt
simple_asr-0.0.1.dist-info/top_level.txt
simple_asr-0.0.1.dist-info/RECORD
