Metadata-Version: 2.1
Name: simple-asr
Version: 0.0.1
Summary: Wrapper module around wav2vec2 designed for ease of use
Home-page: http://github.com/mr-martian/simple-asr
Author: Daniel Swanson
Author-email: asr@dangswan.com
License: MIT
Keywords: asr,wav2vec2
License-File: LICENSE
Requires-Dist: datasets
Requires-Dist: evaluate
Requires-Dist: jiwer
Requires-Dist: torchaudio
Requires-Dist: transformers[torch] ~=4.35
Requires-Dist: pyAudioAnalysis ==0.3.14
Requires-Dist: eyeD3 >=0.9.6
Requires-Dist: hmmlearn >=0.2.5
Requires-Dist: imblearn
Requires-Dist: plotly >=5.3.1
